edge_pydb/__init__.py
edge_pydb/_astropy_init.py
edge_pydb/beam_sample.py
edge_pydb/conversion.py
edge_pydb/fitsextract.py
edge_pydb/hexgrid.py
edge_pydb/plotting.py
edge_pydb/util.py
edge_pydb/version.py
edge_pydb/dat_glob/califa/edge_califa.csv
edge_pydb/dat_glob/derived/edge_bbpars_natv.csv
edge_pydb/dat_glob/derived/edge_bbpars_smo7.csv
edge_pydb/dat_glob/derived/edge_jampars.csv
edge_pydb/dat_glob/derived/edge_rdist17.csv
edge_pydb/dat_glob/derived/edge_rfpars.csv
edge_pydb/dat_glob/external/edge_leda.csv
edge_pydb/dat_glob/external/edge_ned.csv
edge_pydb/dat_glob/external/edge_nsa.csv
edge_pydb/dat_glob/external/edge_wise.csv
edge_pydb/dat_glob/obs/edge_coflux_E20.csv
edge_pydb/dat_glob/obs/edge_coflux_natv.csv
edge_pydb/dat_glob/obs/edge_coflux_smo7.csv
edge_pydb/dat_glob/obs/edge_coobs_D.csv
edge_pydb/dat_glob/obs/edge_coobs_DE.csv
edge_pydb/dat_glob/obs/edge_coobs_E.csv
edge_pydb/dat_glob/obs/edge_hiflux.csv
edge_pydb/dat_prof/bbarolo/bb_natv_fitvd_dilmsk.csv
edge_pydb/dat_prof/bbarolo/bb_natv_fitvd_dilmsk_freepa.csv
edge_pydb/dat_prof/bbarolo/bb_natv_fixvd_dilmsk.csv
edge_pydb/dat_prof/bbarolo/bb_natv_fixvd_dilmsk_freepa.csv
edge_pydb/dat_prof/bbarolo/bb_smo7_fitvd_dilmsk.csv
edge_pydb/dat_prof/bbarolo/bb_smo7_fitvd_dilmsk_freepa.csv
edge_pydb/dat_prof/bbarolo/bb_smo7_fixvd_dilmsk.csv
edge_pydb/dat_prof/bbarolo/bb_smo7_fixvd_dilmsk_freepa.csv
edge_pydb/dat_prof/radprof/rprof_de20_smo.csv
edge_pydb/dat_prof/radprof/rprof_smo7_smo.csv
edge_pydb/dat_prof/rotcur_leung/jam_rotcurves.csv
edge_pydb/dat_prof/rotcur_levy/rf_CO_natv.csv
edge_pydb/dat_prof/rotcur_levy/rf_CO_smo6.csv
edge_pydb/dat_prof/rotcur_levy/rf_HA_natv.csv
edge_pydb/dat_prof/rotcur_levy/rf_HA_smo6.csv
edge_pydb/img_califa/NGC4047_allpix.pipe3d.hdf5
edge_pydb/img_califa/__init__.py
edge_pydb/img_califa/do_pipe3d.py
edge_pydb/img_califa/do_pycasso.py
edge_pydb/img_cocube/NGC4047.cocube_smo7.hdf5
edge_pydb/img_comom/NGC4047.2d_smo7.hdf5
edge_pydb/img_comom/NGC4047_hex.2d_smo7.hdf5
edge_pydb-1.8.0.dist-info/LICENSE
edge_pydb-1.8.0.dist-info/METADATA
edge_pydb-1.8.0.dist-info/WHEEL
edge_pydb-1.8.0.dist-info/top_level.txt
edge_pydb-1.8.0.dist-info/RECORD
