Metadata-Version: 2.1
Name: edge_pydb
Version: 1.8.0
Summary: Python based database for CARMA EDGE
Home-page: https://github.com/tonywong94/edge_pydb
Author: Tony Wong and Yufeng Luo
Author-email: wongt@illinois.edu
License: BSD 3-Clause License
Classifier: Intended Audience :: Science/Research
Classifier: License :: OSI Approved :: BSD License
Classifier: Operating System :: OS Independent
Classifier: Programming Language :: Python :: 3
Classifier: Topic :: Scientific/Engineering :: Astronomy
License-File: LICENSE
Requires-Dist: numpy
Requires-Dist: scipy
Requires-Dist: astropy
Requires-Dist: pandas
Requires-Dist: radio-beam
Requires-Dist: matplotlib
Requires-Dist: requests
Requires-Dist: h5py
Requires-Dist: uncertainties
Provides-Extra: do_pipe3d
Requires-Dist: pyFIT3D ; extra == 'do_pipe3d'
Requires-Dist: photutils ; extra == 'do_pipe3d'
Requires-Dist: reproject ; extra == 'do_pipe3d'
Requires-Dist: CO-conversion-factor ; extra == 'do_pipe3d'
Provides-Extra: docs
Requires-Dist: sphinx-astropy ; extra == 'docs'
Requires-Dist: matplotlib ; extra == 'docs'
